README.md
setup.py
enconf/__init__.py
enconf/enconf.py
enconf/version.py
enconf.egg-info/PKG-INFO
enconf.egg-info/SOURCES.txt
enconf.egg-info/dependency_links.txt
enconf.egg-info/requires.txt
enconf.egg-info/top_level.txt