Metadata-Version: 2.1
Name: enconf
Version: 1.0.0.dev7
Summary: Easy config setup from the environment
Home-page: https://github.com/danielunderwood/enconf
Author: Daniel Underwood
License: MIT
Platform: UNKNOWN
Provides-Extra: test
